cutty/__init__.py
cutty/__main__.py
cutty/compat/__init__.py
cutty/compat/contextlib.py
cutty/entrypoints/__init__.py
cutty/entrypoints/cli/__init__.py
cutty/entrypoints/cli/_main.py
cutty/entrypoints/cli/cookiecutter.py
cutty/entrypoints/cli/create.py
cutty/entrypoints/cli/errors.py
cutty/entrypoints/cli/import_.py
cutty/entrypoints/cli/link.py
cutty/entrypoints/cli/update.py
cutty/errors.py
cutty/filestorage/__init__.py
cutty/filestorage/adapters/__init__.py
cutty/filestorage/adapters/cookiecutter.py
cutty/filestorage/adapters/disk.py
cutty/filestorage/adapters/observers/__init__.py
cutty/filestorage/adapters/observers/cookiecutter.py
cutty/filestorage/domain/__init__.py
cutty/filestorage/domain/files.py
cutty/filestorage/domain/observers.py
cutty/filestorage/domain/storage.py
cutty/filesystems/__init__.py
cutty/filesystems/adapters/__init__.py
cutty/filesystems/adapters/dict.py
cutty/filesystems/adapters/disk.py
cutty/filesystems/adapters/git.py
cutty/filesystems/adapters/zip.py
cutty/filesystems/domain/__init__.py
cutty/filesystems/domain/filesystem.py
cutty/filesystems/domain/nodefs.py
cutty/filesystems/domain/path.py
cutty/filesystems/domain/pathfs.py
cutty/filesystems/domain/purepath.py
cutty/packages/__init__.py
cutty/packages/adapters/__init__.py
cutty/packages/adapters/fetchers/__init__.py
cutty/packages/adapters/fetchers/file.py
cutty/packages/adapters/fetchers/ftp.py
cutty/packages/adapters/fetchers/git.py
cutty/packages/adapters/fetchers/http.py
cutty/packages/adapters/fetchers/mercurial.py
cutty/packages/adapters/providers/__init__.py
cutty/packages/adapters/providers/disk.py
cutty/packages/adapters/providers/git.py
cutty/packages/adapters/providers/mercurial.py
cutty/packages/adapters/providers/zip.py
cutty/packages/adapters/registry.py
cutty/packages/adapters/storage.py
cutty/packages/domain/__init__.py
cutty/packages/domain/fetchers.py
cutty/packages/domain/loader.py
cutty/packages/domain/locations.py
cutty/packages/domain/matchers.py
cutty-0.18.0.dist-info/entry_points.txt
cutty-0.18.0.dist-info/LICENSE.rst
cutty-0.18.0.dist-info/WHEEL
cutty-0.18.0.dist-info/METADATA
cutty-0.18.0.dist-info/RECORD
