Metadata-Version: 2.1
Name: cutty
Version: 0.18.0
Summary: cutty
Home-page: https://github.com/cjolowicz/cutty
License: MIT
Author: Claudio Jolowicz
Author-email: mail@claudiojolowicz.com
Requires-Python: >=3.9,<4.0
Classifier: Development Status :: 3 - Alpha
Classifier: License :: OSI Approved :: MIT License
Classifier: Programming Language :: Python :: 3
Classifier: Programming Language :: Python :: 3.10
Classifier: Programming Language :: Python :: 3.9
Requires-Dist: Jinja2 (>=2.11.3,<4.0.0)
Requires-Dist: Pygments (>=2.10.0,<3.0.0)
Requires-Dist: binaryornot (>=0.4.4,<0.5.0)
Requires-Dist: click (>=8.0.1,<9.0.0)
Requires-Dist: httpx (>=0.18.1,<0.22.0)
Requires-Dist: jinja2-time (>=0.2.0,<0.3.0)
Requires-Dist: platformdirs (>=2.0.2,<3.0.0)
Requires-Dist: prompt-toolkit (>=3.0.22,<4.0.0)
Requires-Dist: pygit2 (>=1.7.0,<2.0.0)
Requires-Dist: python-slugify (>=5.0.0,<6.0.0)
Requires-Dist: questionary (>=1.10.0,<2.0.0)
Requires-Dist: yarl (>=1.6.3,<2.0.0)
Project-URL: Changelog, https://github.com/cjolowicz/cutty/releases
Project-URL: Documentation, https://cutty.readthedocs.io
Project-URL: Repository, https://github.com/cjolowicz/cutty
